w3bstream_client_python/__init__.py
w3bstream_client_python/client.py
w3bstream_client_python-1.0.1.dist-info/LICENSE
w3bstream_client_python-1.0.1.dist-info/METADATA
w3bstream_client_python-1.0.1.dist-info/WHEEL
w3bstream_client_python-1.0.1.dist-info/top_level.txt
w3bstream_client_python-1.0.1.dist-info/RECORD
