Metadata-Version: 2.1
Name: w3bstream-client-python
Version: 1.0.1
Summary: Official W3bstream Client for Python
License-File: LICENSE
Requires-Dist: requests
Requires-Dist: typeguard
